CONTRIBUTING.md
LICENSE
MANIFEST.in
README.md
settings.ini
setup.py
ediscovery/__init__.py
ediscovery/_nbdev.py
ediscovery/core.py
ediscovery.egg-info/PKG-INFO
ediscovery.egg-info/SOURCES.txt
ediscovery.egg-info/dependency_links.txt
ediscovery.egg-info/entry_points.txt
ediscovery.egg-info/not-zip-safe
ediscovery.egg-info/top_level.txt