Metadata-Version: 2.1
Name: ediscovery
Version: 0.0.1
Summary: nlp tool
Home-page: UNKNOWN
Author: amaiya
Author-email: arun@maiya.net
License: Apache Software License 2.0
Keywords: nlp
Platform: UNKNOWN
Classifier: Development Status :: 3 - Alpha
Classifier: Intended Audience :: Developers
Classifier: Natural Language :: English
Classifier: Programming Language :: Python :: 3.6
Classifier: Programming Language :: Python :: 3.7
Classifier: Programming Language :: Python :: 3.8
Classifier: License :: OSI Approved :: Apache Software License
Requires-Python: >=3.6
